MANIFEST.in
README.rst
enumit.py
setup.cfg
setup.py
enumit.egg-info/PKG-INFO
enumit.egg-info/SOURCES.txt
enumit.egg-info/dependency_links.txt
enumit.egg-info/top_level.txt