Metadata-Version: 1.1
Name: enumit
Version: 1.2
Summary: Enumeration library for python.
Home-page: https://github.com/farukcepni/enumit
Author: Faruk Cepni
Author-email: farukcepni@gmail.com
License: UNKNOWN
Keywords: enumeration,enum
Platform: UNKNOWN
Classifier: Development Status :: 3 - Alpha
Classifier: Environment :: Web Environment
Classifier: Intended Audience :: Developers
Classifier: License :: OSI Approved :: BSD License
Classifier: Operating System :: OS Independent
Classifier: Programming Language :: Python
